{
  "language": "ndebele",
  "metrics": {
    "wer": 0.26632762312633834,
    "cer": 0.0658578251926228
  },
  "phoneme_substitutions": [
    {
      "substitution": "n → a",
      "count": 261
    },
    {
      "substitution": "a → n",
      "count": 246
    },
    {
      "substitution": "g → n",
      "count": 158
    },
    {
      "substitution": "i → n",
      "count": 156
    },
    {
      "substitution": "e → n",
      "count": 150
    },
    {
      "substitution": "n → e",
      "count": 144
    },
    {
      "substitution": "a → l",
      "count": 143
    },
    {
      "substitution": "n → i",
      "count": 139
    },
    {
      "substitution": "u → k",
      "count": 133
    },
    {
      "substitution": "a → m",
      "count": 126
    }
  ],
  "examples": [
    {
      "reference": "liiri lesihlanu",
      "hypothesis": "liiri n lesihlanu",
      "subs": {
        "l → n": 1,
        "e → l": 1,
        "s → e": 1,
        "i → s": 1,
        "h → i": 1,
        "l → h": 1,
        "a → l": 1,
        "n → a": 1,
        "u → n": 1
      },
      "morphological_errors": {
        "misaligned": true,
        "errors": [
          [
            "lesihlanu",
            "n"
          ]
        ]
      }
    },
    {
      "reference": "esiyabuswa",
      "hypothesis": "itiyabuswa",
      "subs": {
        "e → i": 1,
        "s → t": 1
      },
      "morphological_errors": {
        "misaligned": false,
        "errors": [
          [
            "esiyabuswa",
            "itiyabuswa"
          ]
        ]
      }
    },
    {
      "reference": "amapholisa wekhethu la adlange khulu",
      "hypothesis": "amapholisa n wekhethu la adlange khulu",
      "subs": {
        "w → n": 1,
        "e → w": 1,
        "k → e": 2,
        "h → k": 2,
        "e → h": 1,
        "t → e": 1,
        "h → t": 1,
        "u → h": 2,
        "l → u": 2,
        "a → l": 2,
        "d → a": 1,
        "l → d": 1,
        "n → a": 1,
        "g → n": 1,
        "e → g": 1,
        "u → l": 1
      },
      "morphological_errors": {
        "misaligned": true,
        "errors": [
          [
            "wekhethu",
            "n"
          ],
          [
            "la",
            "wekhethu"
          ],
          [
            "adlange",
            "la"
          ],
          [
            "khulu",
            "adlange"
          ]
        ]
      }
    },
    {
      "reference": "ngumuntu wembaji",
      "hypothesis": "imuntu wembaji",
      "subs": {
        "n → i": 1,
        "g → m": 1,
        "m → n": 1,
        "u → t": 1,
        "n → u": 1,
        "t → w": 1,
        "u → e": 1,
        "w → m": 1,
        "e → b": 1,
        "m → a": 1,
        "b → j": 1,
        "a → i": 1
      },
      "morphological_errors": {
        "misaligned": false,
        "errors": [
          [
            "ngumuntu",
            "imuntu"
          ]
        ]
      }
    },
    {
      "reference": "limhlana amalanga alitjhumi nantathu kuvelabahlinze",
      "hypothesis": "limhlanu amalanga alitjhumi nentathu kuvelabahlinze",
      "subs": {
        "a → u": 1,
        "a → e": 1
      },
      "morphological_errors": {
        "misaligned": false,
        "errors": [
          [
            "limhlana",
            "limhlanu"
          ],
          [
            "nantathu",
            "nentathu"
          ]
        ]
      }
    },
    {
      "reference": "e midran",
      "hypothesis": "enitreni",
      "subs": {
        "m → n": 1,
        "d → t": 1,
        "a → e": 1
      },
      "morphological_errors": {
        "misaligned": true,
        "errors": [
          [
            "e",
            "enitreni"
          ]
        ]
      }
    },
    {
      "reference": "nginamasumi amathathu nathoba",
      "hypothesis": "ngiyobu namazimu amathathu nathoba",
      "subs": {
        "n → y": 1,
        "a → o": 1,
        "m → b": 1,
        "a → u": 1,
        "s → n": 1,
        "u → a": 1,
        "i → a": 1,
        "a → z": 1,
        "m → i": 1,
        "a → m": 2,
        "t → u": 1,
        "h → a": 1,
        "t → a": 1,
        "h → t": 1,
        "u → h": 1,
        "n → a": 1,
        "a → t": 2,
        "t → h": 1,
        "h → u": 1,
        "o → n": 1,
        "b → a": 1
      },
      "morphological_errors": {
        "misaligned": true,
        "errors": [
          [
            "nginamasumi",
            "ngiyobu"
          ],
          [
            "amathathu",
            "namazimu"
          ],
          [
            "nathoba",
            "amathathu"
          ]
        ]
      }
    },
    {
      "reference": "angatjhadi",
      "hypothesis": "angatjhadi n",
      "subs": {},
      "morphological_errors": {
        "misaligned": true,
        "errors": []
      }
    },
    {
      "reference": "zitjho iinlori ngaphandle kube buvuruvuru",
      "hypothesis": "zitjho iinlori ngaphandle kube n buvuruvuru",
      "subs": {
        "b → n": 1,
        "u → b": 1,
        "v → u": 2,
        "u → v": 2,
        "r → u": 2,
        "u → r": 2
      },
      "morphological_errors": {
        "misaligned": true,
        "errors": [
          [
            "buvuruvuru",
            "n"
          ]
        ]
      }
    },
    {
      "reference": "izokutholakala ngokobana umntwana aye esikolweni",
      "hypothesis": "izokutholakala n ngokobana umntwana aye esikolweni",
      "subs": {
        "g → n": 1,
        "o → g": 1,
        "k → o": 1,
        "o → k": 2,
        "b → o": 1,
        "a → b": 1,
        "n → a": 2,
        "a → n": 2,
        "u → a": 1,
        "m → u": 1,
        "n → m": 1,
        "t → n": 1,
        "w → t": 1,
        "a → w": 1,
        "y → a": 1,
        "e → y": 1,
        "s → e": 1,
        "i → s": 1,
        "k → i": 1,
        "l → o": 1,
        "w → l": 1,
        "e → w": 1,
        "n → e": 1,
        "i → n": 1
      },
      "morphological_errors": {
        "misaligned": true,
        "errors": [
          [
            "ngokobana",
            "n"
          ],
          [
            "umntwana",
            "ngokobana"
          ],
          [
            "aye",
            "umntwana"
          ],
          [
            "esikolweni",
            "aye"
          ]
        ]
      }
    },
    {
      "reference": "matjhumi amabili nesithandathu",
      "hypothesis": "umatjhumi wobili nesikhalathu",
      "subs": {
        "m → u": 2,
        "a → m": 1,
        "t → a": 1,
        "j → t": 1,
        "h → j": 1,
        "u → h": 1,
        "i → m": 1,
        "a → i": 1,
        "m → w": 1,
        "a → o": 1,
        "t → k": 1,
        "n → l": 1,
        "d → a": 1,
        "a → t": 1,
        "t → h": 1,
        "h → u": 1
      },
      "morphological_errors": {
        "misaligned": false,
        "errors": [
          [
            "matjhumi",
            "umatjhumi"
          ],
          [
            "amabili",
            "wobili"
          ],
          [
            "nesithandathu",
            "nesikhalathu"
          ]
        ]
      }
    },
    {
      "reference": "isindebele",
      "hypothesis": "n isindebele",
      "subs": {
        "i → n": 1,
        "s → i": 1,
        "i → s": 1,
        "n → i": 1,
        "d → n": 1,
        "e → d": 1,
        "b → e": 1,
        "e → b": 1,
        "l → e": 1,
        "e → l": 1
      },
      "morphological_errors": {
        "misaligned": true,
        "errors": [
          [
            "isindebele",
            "n"
          ]
        ]
      }
    },
    {
      "reference": "sindebele",
      "hypothesis": "kandebele",
      "subs": {
        "s → k": 1,
        "i → a": 1
      },
      "morphological_errors": {
        "misaligned": false,
        "errors": [
          [
            "sindebele",
            "kandebele"
          ]
        ]
      }
    },
    {
      "reference": "lilanga lesikhombisa kusihlaba intangana",
      "hypothesis": "lilanga n lesikhombisa kusihlaba intangana",
      "subs": {
        "l → n": 1,
        "e → l": 1,
        "s → e": 1,
        "i → s": 2,
        "k → i": 1,
        "h → k": 1,
        "o → h": 1,
        "m → o": 1,
        "b → m": 1,
        "i → b": 1,
        "s → i": 1,
        "a → s": 1,
        "k → a": 1,
        "u → k": 1,
        "s → u": 1,
        "h → i": 1,
        "l → h": 1,
        "a → l": 1,
        "b → a": 1,
        "a → b": 1,
        "i → a": 1,
        "n → i": 1,
        "t → n": 1,
        "a → t": 1,
        "n → a": 2,
        "g → n": 1,
        "a → g": 1,
        "a → n": 1
      },
      "morphological_errors": {
        "misaligned": true,
        "errors": [
          [
            "lesikhombisa",
            "n"
          ],
          [
            "kusihlaba",
            "lesikhombisa"
          ],
          [
            "intangana",
            "kusihlaba"
          ]
        ]
      }
    },
    {
      "reference": "iye ngitjhadile",
      "hypothesis": "iinyo ngitjhadile",
      "subs": {
        "y → i": 1,
        "e → n": 1,
        "n → y": 1,
        "g → o": 1,
        "i → n": 1,
        "t → g": 1,
        "j → i": 1,
        "h → t": 1,
        "a → j": 1,
        "d → h": 1,
        "i → a": 1,
        "l → d": 1,
        "e → i": 1
      },
      "morphological_errors": {
        "misaligned": false,
        "errors": [
          [
            "iye",
            "iinyo"
          ]
        ]
      }
    },
    {
      "reference": "amapholisa wekhethu la adlange khulu",
      "hypothesis": "namapholisa wekhethu la adlange khu",
      "subs": {
        "a → n": 1,
        "m → a": 1,
        "a → m": 1,
        "p → a": 1,
        "h → p": 1,
        "o → h": 1,
        "l → o": 1,
        "i → l": 1,
        "s → i": 1,
        "a → s": 1,
        "w → a": 1,
        "e → w": 1,
        "k → e": 2,
        "h → k": 2,
        "e → h": 1,
        "t → e": 1,
        "h → t": 1,
        "u → h": 2,
        "l → u": 2,
        "a → l": 2,
        "d → a": 1,
        "l → d": 1,
        "n → a": 1,
        "g → n": 1,
        "e → g": 1
      },
      "morphological_errors": {
        "misaligned": false,
        "errors": [
          [
            "amapholisa",
            "namapholisa"
          ],
          [
            "khulu",
            "khu"
          ]
        ]
      }
    },
    {
      "reference": "ngineminyaka emasumi amathathu nasithandath",
      "hypothesis": "yaminyaka ematjhumi amathathu nasithandath",
      "subs": {
        "n → y": 1,
        "g → a": 1,
        "i → m": 1,
        "n → i": 1,
        "e → n": 1,
        "m → y": 1,
        "i → a": 2,
        "n → k": 1,
        "y → a": 1,
        "a → e": 1,
        "k → m": 1,
        "e → t": 1,
        "m → j": 1,
        "a → h": 1,
        "s → u": 1,
        "u → m": 1,
        "m → i": 1,
        "a → m": 1,
        "m → a": 1,
        "a → t": 3,
        "t → h": 4,
        "h → a": 2,
        "h → u": 1,
        "u → n": 1,
        "n → a": 1,
        "a → s": 1,
        "s → i": 1,
        "i → t": 1,
        "a → n": 1,
        "n → d": 1,
        "d → a": 1
      },
      "morphological_errors": {
        "misaligned": false,
        "errors": [
          [
            "ngineminyaka",
            "yaminyaka"
          ],
          [
            "emasumi",
            "ematjhumi"
          ]
        ]
      }
    },
    {
      "reference": "yafike yaqondama esiginindeni ngesinceleni sikazomba",
      "hypothesis": "ngafika yaqondama esiginindeni n ngesinceleni sikazomba",
      "subs": {
        "y → n": 1,
        "a → g": 1,
        "f → a": 1,
        "i → f": 1,
        "k → i": 1,
        "e → k": 1,
        "y → a": 1,
        "a → y": 1,
        "q → a": 1,
        "o → q": 1,
        "n → o": 1,
        "d → n": 2,
        "a → d": 1,
        "m → a": 1,
        "a → m": 2,
        "e → a": 1,
        "s → e": 1,
        "i → s": 1,
        "g → i": 1,
        "i → g": 1,
        "n → i": 3,
        "i → n": 2,
        "e → d": 1,
        "n → e": 1,
        "g → n": 1,
        "e → n": 2,
        "s → g": 1,
        "i → e": 2,
        "n → s": 1,
        "c → i": 1,
        "l → c": 1,
        "n → l": 1,
        "s → n": 1,
        "k → s": 1,
        "a → i": 1,
        "z → k": 1,
        "o → a": 1,
        "m → z": 1,
        "b → o": 1
      },
      "morphological_errors": {
        "misaligned": true,
        "errors": [
          [
            "yafike",
            "ngafika"
          ],
          [
            "ngesinceleni",
            "n"
          ],
          [
            "sikazomba",
            "ngesinceleni"
          ]
        ]
      }
    },
    {
      "reference": "e middelburg",
      "hypothesis": "inusipheke",
      "subs": {
        "e → i": 1,
        "m → n": 1,
        "i → u": 1,
        "d → s": 1,
        "d → i": 1,
        "e → p": 1,
        "l → h": 1,
        "b → e": 1,
        "u → k": 1,
        "r → e": 1
      },
      "morphological_errors": {
        "misaligned": true,
        "errors": [
          [
            "e",
            "inusipheke"
          ]
        ]
      }
    },
    {
      "reference": "muntu wengubo",
      "hypothesis": "umuntu wengubo",
      "subs": {
        "m → u": 1,
        "u → m": 1,
        "n → u": 1,
        "t → n": 1,
        "u → t": 1,
        "w → u": 1,
        "e → w": 1,
        "n → e": 1,
        "g → n": 1,
        "u → g": 1,
        "b → u": 1,
        "o → b": 1
      },
      "morphological_errors": {
        "misaligned": false,
        "errors": [
          [
            "muntu",
            "umuntu"
          ]
        ]
      }
    }
  ],
  "notes": {
    "Substitution note": "These are character level substitutions which are used to approximate phoneme confusion.",
    "Morphological analysis note": "Morphological errors include stem mismatches and prefix/suffix mismatches."
  }
}